{
  "items": [
    {
      "title": "Хуманоиден робот бяга най-бързо на полумаратон в Пекин, ''постави'' световен рекорд",
      "link": "https://offnews.bg/sviat/humanoiden-robot-biaga-naj-barzo-na-polumaraton-v-pekin-postavi-s-865219.html",
      "pubDate": "2026-04-19 04:50:19",
      "thumbnail": {
        "link": "https://i2.offnews.bg/events/2026/04/19/865219/phpiqjwv5_152x158.jpg",
        "type": "image/jpeg",
        "length": 7739
      },
      "source": {
        "name": "OffNews",
        "color": "#E91E63"
      }
    },
    {
      "title": "Иран: Има напредък в преговорите със САЩ",
      "link": "https://offnews.bg/sviat/iran-ima-napredak-v-pregovorite-sas-sasht-865218.html",
      "pubDate": "2026-04-19 04:31:10",
      "thumbnail": {
        "link": "https://i2.offnews.bg/events/2026/04/19/865218/phpswu2tg_152x158.jpg",
        "type": "image/jpeg",
        "length": 7576
      },
      "source": {
        "name": "OffNews",
        "color": "#E91E63"
      }
    },
    {
      "title": "Избираме 240 от 4783 кандидати за депутати",
      "link": "https://offnews.bg/izbori/izbirame-240-ot-4783-kandidati-za-deputati-865217.html",
      "pubDate": "2026-04-19 04:00:41",
      "thumbnail": {
        "link": "https://i2.offnews.bg/events/2026/04/19/865217/phpnaj5b5_152x158.jpg",
        "type": "image/jpeg",
        "length": 4270
      },
      "source": {
        "name": "OffNews",
        "color": "#E91E63"
      }
    },
    {
      "title": "Слънчево до обяд, после облаци и дъжд на места",
      "link": "https://offnews.bg/obshtestvo/slanchevo-do-obiad-posle-oblatci-i-dazhd-na-mesta-865211.html",
      "pubDate": "2026-04-19 03:26:53",
      "thumbnail": {
        "link": "https://i2.offnews.bg/events/2026/04/19/865211/phpz7fld4_152x158.jpg",
        "type": "image/jpeg",
        "length": 12012
      },
      "source": {
        "name": "OffNews",
        "color": "#E91E63"
      }
    },
    {
      "title": "Великденските празници свършват днес, Томина неделя е",
      "link": "https://offnews.bg/obshtestvo/velikdenskite-praznitci-svarshvat-dnes-tomina-nedelia-e-822587.html",
      "pubDate": "2026-04-19 02:14:04",
      "thumbnail": {
        "link": "https://i2.offnews.bg/events/2024/05/07/822587/phpi6pjub_152x158.jpg",
        "type": "image/jpeg",
        "length": 6349
      },
      "source": {
        "name": "OffNews",
        "color": "#E91E63"
      }
    },
    {
      "title": "Доган гласува за \"повече държавност\" и обърна внимание на младите",
      "link": "https://www.dnevnik.bg/izbori-2026/2026/04/19/4904037_dogan_glasuva_za_poveche_durjavnost_i_oburna_vnimanie/?ref=rss",
      "pubDate": "2026-04-19 05:01:00",
      "thumbnail": null,
      "source": {
        "name": "Dnevnik",
        "color": "#2196F3"
      }
    },
    {
      "title": "\"Моят кулинарен дневник\" на Стенли Тучи (откъс)",
      "link": "https://www.dnevnik.bg/bacchus/2026/04/19/4903598_moiat_kulinaren_dnevnik_na_stenli_tuchi_otkus/?ref=rss",
      "pubDate": "2026-04-19 05:00:00",
      "thumbnail": null,
      "source": {
        "name": "Dnevnik",
        "color": "#2196F3"
      }
    },
    {
      "title": "Mediterra Restaurant &amp; Wine Bar – вкусът на Средиземноморието в сърцето на София",
      "link": "https://www.dnevnik.bg/bacchus/2026/04/19/4898294_mediterra_restaurant_wine_bar_vkusut_na/?ref=rss",
      "pubDate": "2026-04-19 05:00:00",
      "thumbnail": null,
      "source": {
        "name": "Dnevnik",
        "color": "#2196F3"
      }
    },
    {
      "title": "Кои са номерата на партиите и коалициите в бюлетината за изборите на 19 април",
      "link": "https://www.dnevnik.bg/izbori-2026/2026/04/19/4903750_koi_sa_nomerata_na_partiite_i_koaliciite_v_bjuletinata/?ref=rss",
      "pubDate": "2026-04-19 04:20:00",
      "thumbnail": null,
      "source": {
        "name": "Dnevnik",
        "color": "#2196F3"
      }
    },
    {
      "title": "Гласуването ще продължи до 20 ч.",
      "link": "https://www.dnevnik.bg/izbori-2026/2026/04/19/4903743_glasuvaneto_shte_produlji_do_20_ch/?ref=rss",
      "pubDate": "2026-04-19 04:15:00",
      "thumbnail": null,
      "source": {
        "name": "Dnevnik",
        "color": "#2196F3"
      }
    },
    {
      "title": "Към 10:00 ч. избирателната активност е 7,7%, отчита &#8222;Алфа Рисърч&#8220;",
      "link": "https://svobodnatochka.bg/kam-1000-ch-izbiratelnata-aktivnost-e-77-otchita-alfa-risarch/",
      "pubDate": "Sun, 19 Apr 2026 08:21:51 +0000",
      "thumbnail": null,
      "source": {
        "name": "Свободна точка",
        "color": "#FF9800"
      }
    },
    {
      "title": "Радев иска нов ВСС и главен прокурор. Мирчев призова за &#8222;свободна България&#8220;. Пеевски избира &#8222;повече държавност&#8220;",
      "link": "https://svobodnatochka.bg/za-po-spravedliva-balgariya-kak-glasuvat-politiczite/",
      "pubDate": "Sun, 19 Apr 2026 07:06:16 +0000",
      "thumbnail": null,
      "source": {
        "name": "Свободна точка",
        "color": "#FF9800"
      }
    },
    {
      "title": "&#8222;Всеки сигнал се проверява&#8220;. Георги Кандев съобщи за 93 сигнала за нарушения от началото на изборния ден",
      "link": "https://svobodnatochka.bg/izborniyat-den-zapochna-bez-narusheniya/",
      "pubDate": "Sun, 19 Apr 2026 06:32:04 +0000",
      "thumbnail": null,
      "source": {
        "name": "Свободна точка",
        "color": "#FF9800"
      }
    },
    {
      "title": "Прокуратурата е наредила проверка срещу карикатуриста Христо Комарницки заради публикация",
      "link": "https://svobodnatochka.bg/prokuraturata-e-naredila-proverka-sresthu-karikaturista-hristo-komarniczki-zaradi-publikacziya/",
      "pubDate": "Sat, 18 Apr 2026 17:34:06 +0000",
      "thumbnail": null,
      "source": {
        "name": "Свободна точка",
        "color": "#FF9800"
      }
    },
    {
      "title": "И в деня за размисъл. МВР откри тефтери с имена на хора в кабинета на селски кмет",
      "link": "https://svobodnatochka.bg/i-v-denya-na-razmisal-mvr-otkri-tefteri-s-imena-na-hora-i-izpisani-czifri-v-kabineta-na-selski-kmet/",
      "pubDate": "Sat, 18 Apr 2026 16:54:00 +0000",
      "thumbnail": null,
      "source": {
        "name": "Свободна точка",
        "color": "#FF9800"
      }
    },
    {
      "title": "Григор Димитров загуби в Монте Карло и изпада от топ 100",
      "link": "https://www.mediapool.bg/grigor-dimitrov-zagubi-v-monte-karlo-i-izpada-ot-top-100-news382131.html",
      "pubDate": "Tue, 07 Apr 2026 17:15:41 +0300",
      "thumbnail": {
        "link": "https://www.mediapool.bg/images/382/medium_26933e62662aa020d6999655f5be274d.jpg"
      },
      "source": {
        "name": "Mediapool",
        "color": "#00BCD4"
      }
    },
    {
      "title": "Пациентите ще оценяват лекари и болници през електронното си досие",
      "link": "https://www.mediapool.bg/patsientite-shte-otsenyavat-lekari-i-bolnitsi-prez-elektronnoto-si-dosie-news382128.html",
      "pubDate": "Tue, 07 Apr 2026 17:13:51 +0300",
      "thumbnail": {
        "link": "https://www.mediapool.bg/images/382/medium_ae1b0b57afbfb6d2d88bdb1cd13c5b92.jpg"
      },
      "source": {
        "name": "Mediapool",
        "color": "#00BCD4"
      }
    },
    {
      "title": "Янкулов отмени избора на европрокурори от кабинета на ГЕРБ",
      "link": "https://www.mediapool.bg/yankulov-otmeni-izbora-na-evroprokurori-ot-kabineta-na-gerb-news382129.html",
      "pubDate": "Tue, 07 Apr 2026 17:06:28 +0300",
      "thumbnail": {
        "link": "https://www.mediapool.bg/images/382/medium_79cdd9787a0136f37bf94992f56b944f.jpg"
      },
      "source": {
        "name": "Mediapool",
        "color": "#00BCD4"
      }
    },
    {
      "title": "Френските граждани Сесил Колер и Жак Пари, осъдени за шпионаж в Иран, са на свобода и пътуват към Франция",
      "link": "https://www.mediapool.bg/frenskite-grazhdani-sesil-koler-i-zhak-pari-osadeni-za-shpionazh-v-iran-sa-na-svoboda-i-patuvat-kam-frantsiya-news382127.html",
      "pubDate": "Tue, 07 Apr 2026 17:00:25 +0300",
      "thumbnail": {
        "link": "https://www.mediapool.bg/images/382/medium_543a72ecc64e33a1340a6fb9579cb5fb.jpg"
      },
      "source": {
        "name": "Mediapool",
        "color": "#00BCD4"
      }
    },
    {
      "title": "Албанският език пак стана основна тема в македонската политика",
      "link": "https://www.mediapool.bg/albanskiyat-ezik-pak-stana-osnovna-tema-v-makedonskata-politika-news382126.html",
      "pubDate": "Tue, 07 Apr 2026 16:47:31 +0300",
      "thumbnail": {
        "link": "https://www.mediapool.bg/images/382/medium_60b6fa2f8d3673346dce50c8ef30db6c.jpg"
      },
      "source": {
        "name": "Mediapool",
        "color": "#00BCD4"
      }
    },
    {
      "title": "Ричард Гиър търси подслон за бездомните",
      "link": "https://www.capital.bg/light/neshta/2026/04/19/4902185_richard_giur_tursi_podslon_za_bezdomnite/?ref=rss",
      "pubDate": "2026-04-19 05:00:00",
      "thumbnail": {
        "link": "http://www.capital.bg/shimg/zx640_4902187.jpg"
      },
      "source": {
        "name": "Capital",
        "color": "#4CAF50"
      }
    },
    {
      "title": "Половината млади българи използват AI. Колко училища са готови за това?",
      "link": "https://www.capital.bg/politika_i_ikonomika/obrazovanie/2026/04/19/4898906_polovinata_mladi_bulgari_izpolzvat_ai_kolko_uchilishta/?ref=rss",
      "pubDate": "2026-04-19 05:00:00",
      "thumbnail": {
        "link": "http://www.capital.bg/shimg/zx640_4899238.jpg"
      },
      "source": {
        "name": "Capital",
        "color": "#4CAF50"
      }
    },
    {
      "title": "AI в клас: по-малко шум, повече работа",
      "link": "https://www.capital.bg/politika_i_ikonomika/obrazovanie/2026/04/19/4896348_ai_v_klas_po-malko_shum_poveche_rabota/?ref=rss",
      "pubDate": "2026-04-19 05:00:00",
      "thumbnail": {
        "link": "http://www.capital.bg/shimg/zx640_4896353.jpg"
      },
      "source": {
        "name": "Capital",
        "color": "#4CAF50"
      }
    },
    {
      "title": "Български прогресивни училища: Следващите десет",
      "link": "https://www.capital.bg/politika_i_ikonomika/obrazovanie/2026/04/19/4898345_bulgarski_progresivni_uchilishta_sledvashtite_deset/?ref=rss",
      "pubDate": "2026-04-19 05:00:00",
      "thumbnail": {
        "link": "http://www.capital.bg/shimg/zx640_4898346.jpg"
      },
      "source": {
        "name": "Capital",
        "color": "#4CAF50"
      }
    },
    {
      "title": "20 въпроса | Велика Прахова, скулпторка",
      "link": "https://www.capital.bg/moiat_capital/lica/2026/04/18/4902176_20_vuprosa_velika_prahova_skulptorka/?ref=rss",
      "pubDate": "2026-04-19 04:30:00",
      "thumbnail": {
        "link": "http://www.capital.bg/shimg/zx640_4902348.jpg"
      },
      "source": {
        "name": "Capital",
        "color": "#4CAF50"
      }
    },
    {
      "title": "Илияна Йотова: Гласувах, за да има скоро работещо Народно събрание и силно правителство",
      "link": "https://www.actualno.com/politics/ilijana-jotova-glasuvah-za-da-ima-skoro-raboteshto-narodno-sybranie-i-silno-pravitelstvo-news_2583315.html",
      "pubDate": "2026-04-19 08:53:00",
      "thumbnail": {
        "link": "https://cdn.actualno.eu/actualno_2013/upload/news/2026/04/19/77d64508672021cec28271fe89438e1d_2583315_1920x1080.jpg",
        "type": "image/jpg"
      },
      "source": {
        "name": "Actualno",
        "color": "#9C27B0"
      }
    },
    {
      "title": "Георги Кандев: Заплахи, черни джипове, купени гласове, 93 сигнала за нарушения (ВИДЕО)",
      "link": "https://www.actualno.com/crime/georgi-kandev-zaplahi-cherni-djipove-kupeni-glasove-93-signala-za-narushenija-video-news_2583317.html",
      "pubDate": "2026-04-19 08:45:00",
      "thumbnail": {
        "link": "https://cdn.actualno.eu/actualno_2013/upload/news/2026/04/19/e010d94c4f7a5bc365e48d907c8bb958_2583317_1920x1080.jpg",
        "type": "image/jpg"
      },
      "source": {
        "name": "Actualno",
        "color": "#9C27B0"
      }
    },
    {
      "title": "Николай Денков: Гласувах за богата, справедлива и европейска България (ВИДЕО)",
      "link": "https://www.actualno.com/politics/nikolaj-denkov-glasuvah-za-bogata-spravedliva-i-evropejska-bylgarija-video-news_2583309.html",
      "pubDate": "2026-04-19 08:20:00",
      "thumbnail": {
        "link": "https://cdn.actualno.eu/actualno_2013/upload/news/2026/04/19/4c462e8855237991791ab93270c67365_2583309_1920x1080.jpg",
        "type": "image/jpg"
      },
      "source": {
        "name": "Actualno",
        "color": "#9C27B0"
      }
    },
    {
      "title": "Румен Радев каза какво първо ще направи след вота (ВИДЕО)",
      "link": "https://www.actualno.com/politics/rumen-radev-kaza-kakvo-pyrvo-shte-napravi-sled-vota-video-news_2583304.html",
      "pubDate": "2026-04-19 08:12:00",
      "thumbnail": {
        "link": "https://cdn.actualno.eu/actualno_2013/upload/news/2026/04/19/90b375a15cb712fdd912b6e66ea1eae1_2583304_1920x1080.jpg",
        "type": "image/jpg"
      },
      "source": {
        "name": "Actualno",
        "color": "#9C27B0"
      }
    },
    {
      "title": "Мадона изненадващо се появи на \"Коачела\" и направи фурор (ВИДЕО)",
      "link": "https://www.actualno.com/music/madona-iznenadvashto-se-pojavi-na-koachela-i-napravi-furor-video-news_2583298.html",
      "pubDate": "2026-04-19 08:00:00",
      "thumbnail": {
        "link": "https://cdn.actualno.eu/actualno_2013/upload/news/2026/04/19/a6e31c31355139b2eedd62209c828ff3_2583298_1920x1080.jpg",
        "type": "image/jpg"
      },
      "source": {
        "name": "Actualno",
        "color": "#9C27B0"
      }
    },
    {
      "title": "Game Devs Explain the Tricks Involved with Letting You Pause a Game",
      "link": "https://kotaku.com/video-game-devs-explain-how-pausing-works-and-sometimes-it-gets-weird-2000686339",
      "pubDate": "2026-04-16 14:05:10",
      "thumbnail": null,
      "source": {
        "name": "Hacker News",
        "color": "#FF6600"
      }
    },
    {
      "title": "NIST scientists create 'any wavelength' lasers",
      "link": "https://www.nist.gov/news-events/news/2026/04/any-color-you-nist-scientists-create-any-wavelength-lasers-tiny-circuits",
      "pubDate": "2026-04-18 20:54:17",
      "thumbnail": null,
      "source": {
        "name": "Hacker News",
        "color": "#FF6600"
      }
    },
    {
      "title": "Anonymous request-token comparisons from Opus 4.6 and Opus 4.7",
      "link": "https://tokens.billchambers.me/leaderboard",
      "pubDate": "2026-04-18 16:05:43",
      "thumbnail": null,
      "source": {
        "name": "Hacker News",
        "color": "#FF6600"
      }
    },
    {
      "title": "What are skiplists good for?",
      "link": "https://antithesis.com/blog/2026/skiptrees/",
      "pubDate": "2026-04-17 13:57:27",
      "thumbnail": null,
      "source": {
        "name": "Hacker News",
        "color": "#FF6600"
      }
    },
    {
      "title": "College instructor turns to typewriters to curb AI-written work",
      "link": "https://sentinelcolorado.com/uncategorized/a-college-instructor-turns-to-typewriters-to-curb-ai-written-work-and-teach-life-lessons/",
      "pubDate": "2026-04-18 19:00:00",
      "thumbnail": null,
      "source": {
        "name": "Hacker News",
        "color": "#FF6600"
      }
    },
    {
      "title": "Germany&apos;s crime figures: Comparing apples to oranges?",
      "link": "https://www.dw.com/en/germany-s-crime-figures-comparing-apples-to-oranges/a-76832148?maca=en-rss-en-top-1022-rdf",
      "pubDate": "2026-04-19T09:21:00Z",
      "thumbnail": null,
      "source": {
        "name": "DW България",
        "color": "#C8102E"
      }
    },
    {
      "title": "Austria: Police find rat poison in recalled baby food jar",
      "link": "https://www.dw.com/en/austria-police-find-rat-poison-in-recalled-baby-food-jar/a-76846811?maca=en-rss-en-top-1022-rdf",
      "pubDate": "2026-04-19T08:37:00Z",
      "thumbnail": null,
      "source": {
        "name": "DW България",
        "color": "#C8102E"
      }
    },
    {
      "title": "Robot runners beat humans in Beijing half-marathon",
      "link": "https://www.dw.com/en/robot-runners-beat-humans-in-beijing-half-marathon/a-76846520?maca=en-rss-en-top-1022-rdf",
      "pubDate": "2026-04-19T08:12:00Z",
      "thumbnail": null,
      "source": {
        "name": "DW България",
        "color": "#C8102E"
      }
    },
    {
      "title": "Attacks on US academics: A microcosm of a larger threat to democracy",
      "link": "https://www.dw.com/en/attacks-on-us-academics-a-microcosm-of-a-larger-threat-to-democracy/a-76777273?maca=en-rss-en-top-1022-rdf",
      "pubDate": "2026-04-19T08:00:00Z",
      "thumbnail": null,
      "source": {
        "name": "DW България",
        "color": "#C8102E"
      }
    },
    {
      "title": "India protests Iran fire on two vessels in Strait of Hormuz",
      "link": "https://www.dw.com/en/india-protests-iran-fire-on-two-vessels-in-strait-of-hormuz/live-76846282?maca=en-rss-en-top-1022-rdf",
      "pubDate": "2026-04-19T07:05:00Z",
      "thumbnail": null,
      "source": {
        "name": "DW България",
        "color": "#C8102E"
      }
    }
  ],
  "lastUpdated": "2026-04-19T09:36:19.079Z"
}