{
  "items": [
    {
      "title": "Откриха отрова за плъхове в бебешка храна в Австрия",
      "link": "https://offnews.bg/sviat/otkriha-otrova-za-plahove-v-bebeshka-hrana-v-avstria-865260.html",
      "pubDate": "2026-04-19 15:25:00",
      "thumbnail": {
        "link": "https://i2.offnews.bg/events/2026/04/19/865260/php6wtnhr_559x345.jpg",
        "type": "image/jpeg",
        "length": 6883
      },
      "source": {
        "name": "OffNews",
        "color": "#E91E63"
      }
    },
    {
      "title": "Грациите завоюваха 1 сребърен и 3 бронзови медала в Баку",
      "link": "https://offnews.bg/gimnastika/gratciite-zavoiuvaha-1-srebaren-i-3-bronzovi-medala-v-baku-865257.html",
      "pubDate": "2026-04-19 15:09:35",
      "thumbnail": {
        "link": "https://i2.offnews.bg/events/2026/04/19/865257/phpjjezgz_559x345.jpg",
        "type": "image/jpeg",
        "length": 8032
      },
      "source": {
        "name": "OffNews",
        "color": "#E91E63"
      }
    },
    {
      "title": "Популярен турски актьор с български корени гласува за първи път в Истанбул",
      "link": "https://offnews.bg/izbori/populiaren-turski-aktior-s-balgarski-koreni-glasuva-za-parvi-pat-v-ist-865256.html",
      "pubDate": "2026-04-19 15:05:42",
      "thumbnail": {
        "link": "https://i2.offnews.bg/events/2026/04/19/865256/phpuckfgp_559x345.jpg",
        "type": "image/jpeg",
        "length": 4971
      },
      "source": {
        "name": "OffNews",
        "color": "#E91E63"
      }
    },
    {
      "title": "328 са сигналите за изборни нарушения към 16:30 часа, съобщава МВР",
      "link": "https://offnews.bg/izbori/328-sa-signalite-za-izborni-narushenia-kam-16-30-chasa-saobshtava-mvr-865253.html",
      "pubDate": "2026-04-19 14:55:27",
      "thumbnail": {
        "link": "https://i2.offnews.bg/events/2026/04/19/865253/phpr8smb1_559x345.jpg",
        "type": "image/jpeg",
        "length": 7323
      },
      "source": {
        "name": "OffNews",
        "color": "#E91E63"
      }
    },
    {
      "title": "Живеещи в София, но без адресна регистрация, избират да гласуват в Сърбия",
      "link": "https://offnews.bg/izbori/zhiveeshti-v-sofia-no-bez-adresna-registratcia-izbirat-da-glasuvat-v-865252.html",
      "pubDate": "2026-04-19 14:54:00",
      "thumbnail": {
        "link": "https://i2.offnews.bg/events/2026/04/19/865252/phpvfd3q6_559x345.jpg",
        "type": "image/jpeg",
        "length": 6297
      },
      "source": {
        "name": "OffNews",
        "color": "#E91E63"
      }
    },
    {
      "title": "Отрова за плъхове бе открита в пюрета на HiPP в Австрия",
      "link": "https://www.dnevnik.bg/sviat/2026/04/19/4904214_otrova_za_pluhove_be_otkrita_v_pjureta_na_hipp_v/?ref=rss",
      "pubDate": "2026-04-19 14:56:00",
      "thumbnail": {
        "link": "https://img.dnevnik.bg/shimg/zx350c_4904233.jpg"
      },
      "source": {
        "name": "Dnevnik",
        "color": "#2196F3"
      }
    },
    {
      "title": "Нищожно малко са проблемите с машините в страната",
      "link": "https://www.dnevnik.bg/izbori-2026/2026/04/19/4904229_nishtojno_malko_sa_problemite_s_mashinite_v_stranata/?ref=rss",
      "pubDate": "2026-04-19 14:52:00",
      "thumbnail": {
        "link": "https://img.dnevnik.bg/shimg/zx350c_4904212.jpg"
      },
      "source": {
        "name": "Dnevnik",
        "color": "#2196F3"
      }
    },
    {
      "title": "Избирателната активност към 16 ч. надхвърли 34%",
      "link": "https://www.dnevnik.bg/izbori-2026/2026/04/19/4904217_izbiratelnata_aktivnost_kum_16_ch_nadhvurli_34/?ref=rss",
      "pubDate": "2026-04-19 14:20:00",
      "thumbnail": {
        "link": "https://img.dnevnik.bg/shimg/zx350c_4904216.jpg"
      },
      "source": {
        "name": "Dnevnik",
        "color": "#2196F3"
      }
    },
    {
      "title": "Гласоподаватели от Смолян се притесняват, че вотът им няма да бъде зачетен заради липсващ печат",
      "link": "https://www.dnevnik.bg/bulgaria/2026/04/19/4904185_glasopodavateli_ot_smolian_se_pritesniavat_che_votut/?ref=rss",
      "pubDate": "2026-04-19 12:54:00",
      "thumbnail": {
        "link": "https://img.dnevnik.bg/shimg/zx350c_4904189.jpg"
      },
      "source": {
        "name": "Dnevnik",
        "color": "#2196F3"
      }
    },
    {
      "title": "Тръмп обвини Иран в \"тотално нарушение на споразумението\" и заплаши с тежки удари",
      "link": "https://www.dnevnik.bg/sviat/2026/04/19/4904183_trum_obiavi_pregovori_s_iran_v_ponedelnik_i_otnovo/?ref=rss",
      "pubDate": "2026-04-19 12:43:00",
      "thumbnail": {
        "link": "https://img.dnevnik.bg/shimg/zx350c_4904184.jpg"
      },
      "source": {
        "name": "Dnevnik",
        "color": "#2196F3"
      }
    },
    {
      "title": "Румен Радев с категорична победа. Какви са първите резултати от изборите",
      "link": "https://svobodnatochka.bg/radev-pobeditel-ekzitpol/",
      "pubDate": "Sun, 19 Apr 2026 18:27:41 +0000",
      "thumbnail": null,
      "source": {
        "name": "Свободна точка",
        "color": "#FF9800"
      }
    },
    {
      "title": "&#8222;Готови сме на различни варианти&#8220;. Радев не каза с кой ще се коалира, но очаква помощ от ПП-ДБ за смяна на Висшия съдебен съвет",
      "link": "https://svobodnatochka.bg/reakcziite/",
      "pubDate": "Sun, 19 Apr 2026 18:11:03 +0000",
      "thumbnail": null,
      "source": {
        "name": "Свободна точка",
        "color": "#FF9800"
      }
    },
    {
      "title": "ИТН, БСП, „Възраждане“. Тези партии са загубили най-много избиратели, гласували за Румен Радев",
      "link": "https://svobodnatochka.bg/itn-bsp-vazrazhdane-tezi-partii-sa-zagubili-naj-mnogo-izbirateli-glasuvali-za-rumen-radev/",
      "pubDate": "Sun, 19 Apr 2026 18:09:10 +0000",
      "thumbnail": null,
      "source": {
        "name": "Свободна точка",
        "color": "#FF9800"
      }
    },
    {
      "title": "Радев е безспорен победител. ГЕРБ губи подкрепа. БСП е на ръба",
      "link": "https://svobodnatochka.bg/radev-e-bezsporen-pobeditel-gerb-gubi-podkrepa-bsp-e-na-raba/",
      "pubDate": "Sun, 19 Apr 2026 17:00:33 +0000",
      "thumbnail": null,
      "source": {
        "name": "Свободна точка",
        "color": "#FF9800"
      }
    },
    {
      "title": "Малко избиратели и групички пред секциите. Как гласува квартал &#8222;Победа&#8220; в Бургас",
      "link": "https://svobodnatochka.bg/kakto-si-e-bilo-pak-si-e-taka-malko-izbirateli-i-grupichki-pred-sekcziite-kak-glasuva-burgaskiyat-kvartal-pobeda/",
      "pubDate": "Sun, 19 Apr 2026 14:55:15 +0000",
      "thumbnail": null,
      "source": {
        "name": "Свободна точка",
        "color": "#FF9800"
      }
    },
    {
      "title": "Григор Димитров загуби в Монте Карло и изпада от топ 100",
      "link": "https://www.mediapool.bg/grigor-dimitrov-zagubi-v-monte-karlo-i-izpada-ot-top-100-news382131.html",
      "pubDate": "Tue, 07 Apr 2026 17:15:41 +0300",
      "thumbnail": {
        "link": "https://www.mediapool.bg/images/382/medium_26933e62662aa020d6999655f5be274d.jpg"
      },
      "source": {
        "name": "Mediapool",
        "color": "#00BCD4"
      }
    },
    {
      "title": "Пациентите ще оценяват лекари и болници през електронното си досие",
      "link": "https://www.mediapool.bg/patsientite-shte-otsenyavat-lekari-i-bolnitsi-prez-elektronnoto-si-dosie-news382128.html",
      "pubDate": "Tue, 07 Apr 2026 17:13:51 +0300",
      "thumbnail": {
        "link": "https://www.mediapool.bg/images/382/medium_ae1b0b57afbfb6d2d88bdb1cd13c5b92.jpg"
      },
      "source": {
        "name": "Mediapool",
        "color": "#00BCD4"
      }
    },
    {
      "title": "Янкулов отмени избора на европрокурори от кабинета на ГЕРБ",
      "link": "https://www.mediapool.bg/yankulov-otmeni-izbora-na-evroprokurori-ot-kabineta-na-gerb-news382129.html",
      "pubDate": "Tue, 07 Apr 2026 17:06:28 +0300",
      "thumbnail": {
        "link": "https://www.mediapool.bg/images/382/medium_79cdd9787a0136f37bf94992f56b944f.jpg"
      },
      "source": {
        "name": "Mediapool",
        "color": "#00BCD4"
      }
    },
    {
      "title": "Френските граждани Сесил Колер и Жак Пари, осъдени за шпионаж в Иран, са на свобода и пътуват към Франция",
      "link": "https://www.mediapool.bg/frenskite-grazhdani-sesil-koler-i-zhak-pari-osadeni-za-shpionazh-v-iran-sa-na-svoboda-i-patuvat-kam-frantsiya-news382127.html",
      "pubDate": "Tue, 07 Apr 2026 17:00:25 +0300",
      "thumbnail": {
        "link": "https://www.mediapool.bg/images/382/medium_543a72ecc64e33a1340a6fb9579cb5fb.jpg"
      },
      "source": {
        "name": "Mediapool",
        "color": "#00BCD4"
      }
    },
    {
      "title": "Албанският език пак стана основна тема в македонската политика",
      "link": "https://www.mediapool.bg/albanskiyat-ezik-pak-stana-osnovna-tema-v-makedonskata-politika-news382126.html",
      "pubDate": "Tue, 07 Apr 2026 16:47:31 +0300",
      "thumbnail": {
        "link": "https://www.mediapool.bg/images/382/medium_60b6fa2f8d3673346dce50c8ef30db6c.jpg"
      },
      "source": {
        "name": "Mediapool",
        "color": "#00BCD4"
      }
    },
    {
      "title": "Избори '26 на живо: Разликата между втория и третия се топи според предварителните резултати, висока избирателната активност",
      "link": "https://www.capital.bg/politika_i_ikonomika/bulgaria/2026/04/19/4903905_izbori_26_na_jivo_shte_ima_li_masovo_glasuvane_i_kolko/?ref=rss",
      "pubDate": "2026-04-19 08:00:00",
      "thumbnail": {
        "link": "http://www.capital.bg/shimg/zx640_4904099.jpg"
      },
      "source": {
        "name": "Capital",
        "color": "#4CAF50"
      }
    },
    {
      "title": "Талантите от \"20 под 20\" | Мартин Атанасов за смисъла да останеш в България и да направиш промяна",
      "link": "https://www.capital.bg/moiat_capital/lica/2026/03/29/4878257_talantite_ot_20_pod_20_martin_atanasov_za_smisula_da/?ref=rss",
      "pubDate": "2026-04-19 07:30:00",
      "thumbnail": {
        "link": "http://www.capital.bg/shimg/zx640_4878258.jpg"
      },
      "source": {
        "name": "Capital",
        "color": "#4CAF50"
      }
    },
    {
      "title": "Батериите за бързо зареждане за електромобилите вече са на път",
      "link": "https://www.capital.bg/biznes/kompanii/2026/04/19/4895518_bateriite_za_burzo_zarejdane_za_elektromobilite_veche/?ref=rss",
      "pubDate": "2026-04-19 07:27:00",
      "thumbnail": {
        "link": "http://www.capital.bg/shimg/zx640_4902743.jpg"
      },
      "source": {
        "name": "Capital",
        "color": "#4CAF50"
      }
    },
    {
      "title": "Инженер на дронове: професията, която ще лети нагоре",
      "link": "https://www.capital.bg/politika_i_ikonomika/pazar-na-truda/2026/04/19/4882825_injener_na_dronove_profesiiata_koiato_shte_leti_nagore/?ref=rss",
      "pubDate": "2026-04-19 07:00:00",
      "thumbnail": {
        "link": "http://www.capital.bg/shimg/zx640_4882823.jpg"
      },
      "source": {
        "name": "Capital",
        "color": "#4CAF50"
      }
    },
    {
      "title": "В търсене на алтернативи",
      "link": "https://www.capital.bg/politika_i_ikonomika/obrazovanie/2026/04/19/4897730_v_tursene_na_alternativi/?ref=rss",
      "pubDate": "2026-04-19 07:00:00",
      "thumbnail": {
        "link": "http://www.capital.bg/shimg/zx640_4902678.jpg"
      },
      "source": {
        "name": "Capital",
        "color": "#4CAF50"
      }
    },
    {
      "title": "МВнР: Приключиха изборите в 6 държави, В Лондон се извиват дълги опашки",
      "link": "https://www.actualno.com/politics/mvnr-prikluchiha-izborite-v-6-dyrjavi-v-london-se-izvivat-dylgi-opashki-news_2583450.html",
      "pubDate": "2026-04-19 15:15:00",
      "thumbnail": {
        "link": "https://cdn.actualno.eu/actualno_2013/upload/news/2026/04/19/8c9e51d173d07aaa14c3da95341c1b51_2583450_1920x1080.jpg",
        "type": "image/jpg"
      },
      "source": {
        "name": "Actualno",
        "color": "#9C27B0"
      }
    },
    {
      "title": "Ливърпул оцеля в щуро историческо дерби с попадение в 100'! Вила спечели луд 7-голов трилър",
      "link": "https://www.actualno.com/football/livyrpul-ocelja-v-shturo-istorichesko-derbi-s-popadenie-v-100-vila-specheli-lud-7-golov-trilyr-news_2583445.html",
      "pubDate": "2026-04-19 15:06:00",
      "thumbnail": {
        "link": "https://cdn.actualno.eu/actualno_2013/upload/news/2026/04/19/68c75088322117f9e97508a575630a57_2583445_1920x1080.jpg",
        "type": "image/jpg"
      },
      "source": {
        "name": "Actualno",
        "color": "#9C27B0"
      }
    },
    {
      "title": "\"Иран по-скоро печели войната. Ормузкият проток няма да бъде отворен в близко бъдеще\": Анализ",
      "link": "https://www.actualno.com/opinion/iran-po-skoro-pecheli-vojnata-ormuzkijat-protok-njama-da-byde-otvoren-v-blizko-bydeshte-analiz-news_2583444.html",
      "pubDate": "2026-04-19 15:06:00",
      "thumbnail": {
        "link": "https://cdn.actualno.eu/actualno_2013/upload/news/2026/04/19/95562650767e5d47d3e7bcc83aba1dec_2583444_1920x1080.jpg",
        "type": "image/jpg"
      },
      "source": {
        "name": "Actualno",
        "color": "#9C27B0"
      }
    },
    {
      "title": "Западни медии: Българите се мобилизираха за изборите, очаква се над 60% да отидат до урните",
      "link": "https://www.actualno.com/politics/zapadni-medii-bylgarite-se-mobiliziraha-za-izborite-ochakva-se-nad-60-da-otidat-do-urnite-news_2583442.html",
      "pubDate": "2026-04-19 15:02:00",
      "thumbnail": {
        "link": "https://cdn.actualno.eu/actualno_2013/upload/news/2026/04/19/001afe32bf2478d70eff0ff38b3aec55_2583442_1920x1080.jpg",
        "type": "image/jpg"
      },
      "source": {
        "name": "Actualno",
        "color": "#9C27B0"
      }
    },
    {
      "title": "Магнитна буря за понеделник, 20 април 2026: Прогноза от САЩ",
      "link": "https://www.actualno.com/cosmos/magnitna-burja-za-ponedelnik-20-april-2026-prognoza-ot-sasht-news_2582519.html",
      "pubDate": "2026-04-19 15:00:00",
      "thumbnail": {
        "link": "https://cdn.actualno.eu/actualno_2013/upload/news/2026/04/17/127cc79709358a3409524c1266594c28_2582519_1920x1080.jpg",
        "type": "image/jpg"
      },
      "source": {
        "name": "Actualno",
        "color": "#9C27B0"
      }
    },
    {
      "title": "Vercel Says Internal Systems Hit in Breach",
      "link": "https://decipher.sc/2026/04/19/vercel-says-internal-systems-hit-in-breach/",
      "pubDate": "2026-04-19 15:23:39",
      "thumbnail": null,
      "source": {
        "name": "Hacker News",
        "color": "#FF6600"
      }
    },
    {
      "title": "Archive of Byte magazine, starting with issue #1 in 1975",
      "link": "https://archive.org/details/byte-magazine-1975-09",
      "pubDate": "2026-04-17 14:07:28",
      "thumbnail": null,
      "source": {
        "name": "Hacker News",
        "color": "#FF6600"
      }
    },
    {
      "title": "Nanopass Framework: Clean Compiler Creation Language",
      "link": "https://nanopass.org/",
      "pubDate": "2026-04-15 11:38:22",
      "thumbnail": null,
      "source": {
        "name": "Hacker News",
        "color": "#FF6600"
      }
    },
    {
      "title": "Notion leaks email addresses of all editors of any public page",
      "link": "https://twitter.com/weezerOSINT/status/2045849358462222720",
      "pubDate": "2026-04-19 15:20:01",
      "thumbnail": null,
      "source": {
        "name": "Hacker News",
        "color": "#FF6600"
      }
    },
    {
      "title": "Game devs explain the tricks involved with letting you pause a game",
      "link": "https://kotaku.com/video-game-devs-explain-how-pausing-works-and-sometimes-it-gets-weird-2000686339",
      "pubDate": "2026-04-16 14:05:10",
      "thumbnail": null,
      "source": {
        "name": "Hacker News",
        "color": "#FF6600"
      }
    },
    {
      "title": "Bayern Munich clinch 35th Bundesliga title",
      "link": "https://www.dw.com/en/bayern-munich-clinch-35th-bundesliga-title/a-76849660?maca=en-rss-en-top-1022-rdf",
      "pubDate": "2026-04-19T17:36:00Z",
      "thumbnail": null,
      "source": {
        "name": "DW България",
        "color": "#C8102E"
      }
    },
    {
      "title": "Bulgaria: Pro-Russian Radev leading after parliamentary vote, exit polls show",
      "link": "https://www.dw.com/en/bulgaria-pro-russian-radev-leading-after-parliamentary-vote-exit-polls-show/a-76846189?maca=en-rss-en-top-1022-rdf",
      "pubDate": "2026-04-19T17:19:00Z",
      "thumbnail": null,
      "source": {
        "name": "DW България",
        "color": "#C8102E"
      }
    },
    {
      "title": "Life in Donbas: &apos;If we give up, there will be nothing left&apos;",
      "link": "https://www.dw.com/en/life-in-donbas-if-we-give-up-there-will-be-nothing-left/a-76794734?maca=en-rss-en-top-1022-rdf",
      "pubDate": "2026-04-19T16:38:00Z",
      "thumbnail": null,
      "source": {
        "name": "DW България",
        "color": "#C8102E"
      }
    },
    {
      "title": "US mass shooting leaves 8 children dead in Louisiana",
      "link": "https://www.dw.com/en/us-mass-shooting-leaves-8-children-dead-in-louisiana/a-76849556?maca=en-rss-en-top-1022-rdf",
      "pubDate": "2026-04-19T16:13:00Z",
      "thumbnail": null,
      "source": {
        "name": "DW България",
        "color": "#C8102E"
      }
    },
    {
      "title": "Mines in the Strait of Hormuz: How dangerous are they?",
      "link": "https://www.dw.com/en/mines-in-the-strait-of-hormuz-how-dangerous-are-they/a-76847658?maca=en-rss-en-top-1022-rdf",
      "pubDate": "2026-04-19T16:00:00Z",
      "thumbnail": null,
      "source": {
        "name": "DW България",
        "color": "#C8102E"
      }
    }
  ],
  "lastUpdated": "2026-04-19T18:29:37.273Z"
}