{
  "items": [
    {
      "title": "Белгия отново се издъни, ВАР помага за 0:0 срещу Иран",
      "link": "https://offnews.bg/futbol/belgia-otnovo-se-izdani-var-pomaga-za-0-0-sreshtu-iran-869156.html",
      "pubDate": "2026-06-21 21:05:03",
      "thumbnail": {
        "link": "https://i2.offnews.bg/events/2026/06/22/869156/phpf4djjb_559x345.jpg",
        "type": "image/jpeg",
        "length": 7238
      },
      "source": {
        "name": "OffNews",
        "color": "#E91E63"
      }
    },
    {
      "title": "Кандидатът на ГЕРБ спечели балотажа за кмет на сливенското село Чинтулово",
      "link": "https://offnews.bg/politika/kandidatat-na-gerb-specheli-balotazha-za-kmet-na-slivenskoto-selo-chin-869155.html",
      "pubDate": "2026-06-21 19:36:01",
      "thumbnail": {
        "link": "https://i2.offnews.bg/events/2026/06/21/869155/phppsn4ob_559x345.jpg",
        "type": "image/jpeg",
        "length": 6298
      },
      "source": {
        "name": "OffNews",
        "color": "#E91E63"
      }
    },
    {
      "title": "Иранската делегация напусна преговорите със САЩ заради обидна публикация на Тръмп",
      "link": "https://offnews.bg/sviat/iranskata-delegatcia-napusna-pregovorite-sas-sasht-zaradi-obidna-publi-869154.html",
      "pubDate": "2026-06-21 19:28:41",
      "thumbnail": {
        "link": "https://i2.offnews.bg/events/2026/06/21/869154/phpnivcrt_559x345.jpg",
        "type": "image/jpeg",
        "length": 5122
      },
      "source": {
        "name": "OffNews",
        "color": "#E91E63"
      }
    },
    {
      "title": "Илияна Йотова: Договорът с Боташ можеше да е в полза на България, но политическите конфликти го провалиха",
      "link": "https://offnews.bg/politika/iliana-jotova-dogovorat-s-botash-mozheshe-da-e-v-polza-na-balgaria-n-869152.html",
      "pubDate": "2026-06-21 18:20:00",
      "thumbnail": {
        "link": "https://i2.offnews.bg/events/2026/06/21/869152/phpeqhuq8_559x345.jpg",
        "type": "image/jpeg",
        "length": 5590
      },
      "source": {
        "name": "OffNews",
        "color": "#E91E63"
      }
    },
    {
      "title": "Испания се върна в играта, Ламин Ямал втори след Пеле",
      "link": "https://offnews.bg/futbol/ispania-se-varna-v-igrata-lamin-iamal-vtori-sled-pele-869153.html",
      "pubDate": "2026-06-21 18:17:34",
      "thumbnail": {
        "link": "https://i2.offnews.bg/events/2026/06/21/869153/php8nvdrg_559x345.jpg",
        "type": "image/jpeg",
        "length": 9050
      },
      "source": {
        "name": "OffNews",
        "color": "#E91E63"
      }
    },
    {
      "title": "Гебрев за отравянето си: Съвместна операция между български управници и руски интереси",
      "link": "https://www.dnevnik.bg/bulgaria/2026/06/21/4927598_gebrev_za_otravianeto_si_suvmestna_operaciia_mejdu/?ref=rss",
      "pubDate": "2026-06-21 17:52:00",
      "thumbnail": {
        "link": "https://img.dnevnik.bg/shimg/zx350c_4032679.jpg"
      },
      "source": {
        "name": "Dnevnik",
        "color": "#2196F3"
      }
    },
    {
      "title": "Осуетени са опити за гласуване с невалидни документи на изборите в село Бата",
      "link": "https://www.dnevnik.bg/bulgaria/2026/06/21/4927595_osueteni_sa_opiti_za_glasuvane_s_nevalidni_dokumenti/?ref=rss",
      "pubDate": "2026-06-21 17:21:00",
      "thumbnail": {
        "link": "https://img.dnevnik.bg/shimg/zx350c_4883078.jpg"
      },
      "source": {
        "name": "Dnevnik",
        "color": "#2196F3"
      }
    },
    {
      "title": "Двама мъже са с опасност за живота след бой и стрелба на варненски плаж",
      "link": "https://www.dnevnik.bg/bulgaria/2026/06/21/4927591_dvama_muje_sa_s_opasnost_za_jivota_sled_boi_i_strelba/?ref=rss",
      "pubDate": "2026-06-21 17:01:00",
      "thumbnail": {
        "link": "https://img.dnevnik.bg/shimg/zx350c_4927592.jpg"
      },
      "source": {
        "name": "Dnevnik",
        "color": "#2196F3"
      }
    },
    {
      "title": "Снимка на деня: Хиляди заляха центъра на Тирана в протест срещу властта",
      "link": "https://www.dnevnik.bg/photos/snimka_na_denia/2026/06/21/4927585_snimka_na_denia_hiliadi_zaliaha_centura_na_tirana_v/?ref=rss",
      "pubDate": "2026-06-21 16:32:00",
      "thumbnail": {
        "link": "https://img.dnevnik.bg/shimg/zx350c_4927586.jpg"
      },
      "source": {
        "name": "Dnevnik",
        "color": "#2196F3"
      }
    },
    {
      "title": "Йотова подкрепи Радев и се обяви срещу санкции за руския патриарх",
      "link": "https://www.dnevnik.bg/politika/2026/06/21/4927587_iotova_podkrepi_radev_i_se_obiavi_sreshtu_sankciite_za/?ref=rss",
      "pubDate": "2026-06-21 16:31:00",
      "thumbnail": {
        "link": "https://img.dnevnik.bg/shimg/zx350c_4927588.jpg"
      },
      "source": {
        "name": "Dnevnik",
        "color": "#2196F3"
      }
    },
    {
      "title": "„Ние сме православна държава“. Йотова подкрепи решението на Радев да защитава от санкции руския патриарх",
      "link": "https://svobodnatochka.bg/novini/yotova-radev-sankcii-patriarh-kiril/",
      "pubDate": "2026-06-21 16:35:10",
      "thumbnail": null,
      "source": {
        "name": "Свободна точка",
        "color": "#FF9800"
      }
    },
    {
      "title": "Ахмед Хасанов е новият главен мюфтия, след като опонентът му се оттегли",
      "link": "https://svobodnatochka.bg/novini/ahmed-hasanov-glaven-miufiya/",
      "pubDate": "2026-06-21 13:09:13",
      "thumbnail": {
        "link": "https://svobodnatochka.bg/wp-content/uploads/2026/06/min_7142-1024x689.jpeg"
      },
      "source": {
        "name": "Свободна точка",
        "color": "#FF9800"
      }
    },
    {
      "title": "В Крим вече не се продава гориво. Украйна удари склад за петрол и инфраструктура за пренос",
      "link": "https://svobodnatochka.bg/novini/krim-gorivo-ukrayna-rusiya/",
      "pubDate": "2026-06-21 11:09:18",
      "thumbnail": null,
      "source": {
        "name": "Свободна точка",
        "color": "#FF9800"
      }
    },
    {
      "title": "„Всичко е в мазут“. Плажове по Черноморието са замърсени. Властите не знаят откъде",
      "link": "https://svobodnatochka.bg/novini/zamarsyavane-plazhove-more-mazut/",
      "pubDate": "2026-06-21 09:14:27",
      "thumbnail": {
        "link": "https://svobodnatochka.bg/wp-content/uploads/2026/06/img_3902-1024x768.jpg"
      },
      "source": {
        "name": "Свободна точка",
        "color": "#FF9800"
      }
    },
    {
      "title": "България води разговори за „цялостно предоговаряне“ на „Боташ“ и очаква резултати след „месец до два“",
      "link": "https://svobodnatochka.bg/novini/botash-sporazumenie-predogovaryane/",
      "pubDate": "2026-06-21 06:44:16",
      "thumbnail": null,
      "source": {
        "name": "Свободна точка",
        "color": "#FF9800"
      }
    },
    {
      "title": "Санкции, православие и енергетика: Илияна Йотова срещу \"кресливите\" критики за патриарх Кирил и \"Лукойл\"",
      "link": "https://www.mediapool.bg/sanktsii-pravoslavie-i-energetika-iliyana-yotova-sreshtu-kreslivite-kritiki-za-patriarh-kiril-i-lukoil-news384665.html",
      "pubDate": "2026-06-21 18:14:41",
      "thumbnail": {
        "link": "https://www.mediapool.bg/images/384/medium_839b118fc083c17b85b3f12f5cdd9628.jpg"
      },
      "source": {
        "name": "Mediapool",
        "color": "#00BCD4"
      }
    },
    {
      "title": "Ахмед Хасанов е избран за нов главен мюфтия",
      "link": "https://www.mediapool.bg/ahmed-hasanov-e-izbran-za-nov-glaven-myuftiya-news384662.html",
      "pubDate": "2026-06-21 14:52:37",
      "thumbnail": {
        "link": "https://www.mediapool.bg/images/384/medium_a43c7750c7639bbbd9be114648d08468.jpg"
      },
      "source": {
        "name": "Mediapool",
        "color": "#00BCD4"
      }
    },
    {
      "title": "Открито е тялото на издирваната туристка в Пирин, кучето й е невредимо",
      "link": "https://www.mediapool.bg/otkrito-e-tyaloto-na-izdirvanata-turistka-v-pirin-kucheto-y-e-nevredimo-news384657.html",
      "pubDate": "2026-06-21 14:27:09",
      "thumbnail": {
        "link": "https://www.mediapool.bg/images/384/medium_e3e248d915cf9c1ca86b520d5892e0ee.jpg"
      },
      "source": {
        "name": "Mediapool",
        "color": "#00BCD4"
      }
    },
    {
      "title": "Настъпи ли прелом във войната на Русия с Украйна",
      "link": "https://www.mediapool.bg/nastapi-li-prelom-vav-voinata-na-rusiya-s-ukraina-news384661.html",
      "pubDate": "2026-06-21 13:46:14",
      "thumbnail": {
        "link": "https://www.mediapool.bg/images/384/medium_b0ef204c19e26c9139dd6e9b4cb3e926.jpg"
      },
      "source": {
        "name": "Mediapool",
        "color": "#00BCD4"
      }
    },
    {
      "title": "Обикновено не свършва добре: ПП и ГЕРБ критикуват позицията на Радев за руските санкции",
      "link": "https://www.mediapool.bg/obiknoveno-ne-svarshva-dobre-pp-i-gerb-kritikuvat-pozitsiyata-na-radev-za-ruskite-sanktsii-news384664.html",
      "pubDate": "2026-06-21 13:43:07",
      "thumbnail": {
        "link": "https://www.mediapool.bg/images/384/medium_dc80a374279078f0423ae08342ff6587.jpg"
      },
      "source": {
        "name": "Mediapool",
        "color": "#00BCD4"
      }
    },
    {
      "title": "Снимка на деня: Настъпи астрономическото лято",
      "link": "https://www.capital.bg/politika_i_ikonomika/sedmicata/2026/06/21/4927540_snimka_na_denia_nastupi_astronomicheskoto_liato/?ref=rss",
      "pubDate": "2026-06-21 11:35:00",
      "thumbnail": {
        "link": "http://www.capital.bg/shimg/zx640_4494522.jpg"
      },
      "source": {
        "name": "Capital",
        "color": "#4CAF50"
      }
    },
    {
      "title": "Клъстер \"София - град на знанието\" ще разработва технологични решения за столицата",
      "link": "https://www.capital.bg/biznes/tehnologii_i_nauka/2026/06/21/4926397_kluster_sofiia_grad_na_znanieto_shte_razrabotva/?ref=rss",
      "pubDate": "2026-06-21 08:53:00",
      "thumbnail": {
        "link": "http://www.capital.bg/shimg/zx640_4926401.jpg"
      },
      "source": {
        "name": "Capital",
        "color": "#4CAF50"
      }
    },
    {
      "title": "Гид | Фестивалите по Черноморието през лято 2026",
      "link": "https://www.capital.bg/moiat_capital/svobodno_vreme/2026/06/21/4910961_gid_festivalite_po_chernomorieto_prez_liato_2026/?ref=rss",
      "pubDate": "2026-06-21 08:26:00",
      "thumbnail": {
        "link": "http://www.capital.bg/shimg/zx640_4911501.jpg"
      },
      "source": {
        "name": "Capital",
        "color": "#4CAF50"
      }
    },
    {
      "title": "Когато бомбите ударят, как туризмът заглъхва",
      "link": "https://www.capital.bg/biznes/turizum/2026/06/21/4918194_kogato_bombite_udariat_kak_turizmut_zagluhva/?ref=rss",
      "pubDate": "2026-06-21 07:51:00",
      "thumbnail": {
        "link": "http://www.capital.bg/shimg/zx640_4926947.jpg"
      },
      "source": {
        "name": "Capital",
        "color": "#4CAF50"
      }
    },
    {
      "title": "Инонг Донг, Amazon: Истинската стойност на креативността идва от човешките опит и интуиция",
      "link": "https://www.capital.bg/biznes/media_i_reklama/2026/06/21/4924496_inong_dong_amazon_istinskata_stoinost_na_kreativnostta/?ref=rss",
      "pubDate": "2026-06-21 07:30:00",
      "thumbnail": {
        "link": "http://www.capital.bg/shimg/zx640_4924505.jpg"
      },
      "source": {
        "name": "Capital",
        "color": "#4CAF50"
      }
    },
    {
      "title": "Доналд Туск: Конфликтът между полски и украински политици е стратегическа грешка",
      "link": "https://www.actualno.com/europe/donald-tusk-konfliktyt-mejdu-polski-i-ukrainski-politici-e-strategicheska-greshka-news_2609522.html",
      "pubDate": "2026-06-21 21:33:00",
      "thumbnail": {
        "link": "https://cdn.actualno.eu/actualno_2013/upload/news/2026/06/21/1978bdaad5886006ab04b81e52dbb408_2609522_1920x1080.jpg",
        "type": "image/jpg"
      },
      "source": {
        "name": "Actualno",
        "color": "#9C27B0"
      }
    },
    {
      "title": "НА ЖИВО: Кризата в Украйна, 22.06.26 - Бензиностанциите в Крим спират да продават гориво",
      "link": "https://www.actualno.com/europe/na-jivo-krizata-v-ukrajna-220626-benzinostanciite-v-krim-spirat-da-prodavat-gorivo-news_2609519.html",
      "pubDate": "2026-06-21 21:22:00",
      "thumbnail": {
        "link": "https://cdn.actualno.eu/actualno_2013/upload/news/2026/06/21/2f2e14e3b853bfad5a39301593ddba40_2609519_1920x1080.jpg",
        "type": "image/jpg"
      },
      "source": {
        "name": "Actualno",
        "color": "#9C27B0"
      }
    },
    {
      "title": "Пълно класиране в груповата фаза на Световното първенство 2026 - още равенства в група G (ОБНОВЕНА)",
      "link": "https://www.actualno.com/football/pylno-klasirane-v-grupovata-faza-na-svetovnoto-pyrvenstvo-2026-oshte-ravenstva-v-grupa-g-obnovena-news_2605278.html",
      "pubDate": "2026-06-21 21:16:00",
      "thumbnail": {
        "link": "https://cdn.actualno.eu/actualno_2013/upload/news/2026/06/10/b44fa7f5c2319979a2e53dcd487b6335_2605278_1920x1080.jpg",
        "type": "image/jpg"
      },
      "source": {
        "name": "Actualno",
        "color": "#9C27B0"
      }
    },
    {
      "title": "Пълни резултати на Световното първенство по футбол 2026 - ето как завършиха последните мачове",
      "link": "https://www.actualno.com/football/pylni-rezultati-na-svetovnoto-pyrvenstvo-po-futbol-2026-eto-kak-zavyrshiha-poslednite-machove-news_2604637.html",
      "pubDate": "2026-06-21 21:16:00",
      "thumbnail": {
        "link": "https://cdn.actualno.eu/actualno_2013/upload/news/2026/06/09/f3fdbfa3732ba72f3f4717ed4ff53e89_2604637_1920x1080.jpg",
        "type": "image/jpg"
      },
      "source": {
        "name": "Actualno",
        "color": "#9C27B0"
      }
    },
    {
      "title": "Класиране за \"Златната ръкавица\" на Световното първенство 2026 - кой е с най-много \"сухи мрежи\"? (ОБНОВЕНА)",
      "link": "https://www.actualno.com/football/klasirane-za-zlatnata-rykavica-na-svetovnoto-pyrvenstvo-2026-koj-e-s-naj-mnogo-suhi-mreji-obnovena-news_2605575.html",
      "pubDate": "2026-06-21 21:14:00",
      "thumbnail": {
        "link": "https://cdn.actualno.eu/actualno_2013/upload/news/2026/06/11/528aadfc7e6c830fdf0275d317aaf3e4_2605575_1920x1080.jpg",
        "type": "image/jpg"
      },
      "source": {
        "name": "Actualno",
        "color": "#9C27B0"
      }
    },
    {
      "title": "Apertus – Open Foundation Model for Sovereign AI",
      "link": "https://apertvs.ai/",
      "pubDate": "2026-06-21 21:29:43",
      "thumbnail": null,
      "source": {
        "name": "Hacker News",
        "color": "#FF6600"
      }
    },
    {
      "title": "Did my old job only exist because of fraud?",
      "link": "https://david.newgas.net/did-my-old-job-only-exist-because-of-fraud/",
      "pubDate": "2026-06-21 21:40:53",
      "thumbnail": null,
      "source": {
        "name": "Hacker News",
        "color": "#FF6600"
      }
    },
    {
      "title": "The Doom Justifies the Valuation",
      "link": "https://geohot.github.io//blog/jekyll/update/2026/06/21/the-doom-justifies-the-valuation.html",
      "pubDate": "2026-06-22 00:45:07",
      "thumbnail": null,
      "source": {
        "name": "Hacker News",
        "color": "#FF6600"
      }
    },
    {
      "title": "Everything is logarithms",
      "link": "https://alexkritchevsky.com/2026/05/25/everything-is-logarithms.html",
      "pubDate": "2026-06-21 21:10:32",
      "thumbnail": null,
      "source": {
        "name": "Hacker News",
        "color": "#FF6600"
      }
    },
    {
      "title": "I was wrong about the Midjourney ultra-sound scanner",
      "link": "https://twitter.com/MattZirwas/status/2068365802491834541",
      "pubDate": "2026-06-21 12:55:08",
      "thumbnail": null,
      "source": {
        "name": "Hacker News",
        "color": "#FF6600"
      }
    },
    {
      "title": "US-Iran talks end in Switzerland, mediators say",
      "link": "https://www.dw.com/en/us-iran-talks-end-in-switzerland-mediators-say/live-77641405?maca=en-rss-en-top-1022-rdf",
      "pubDate": "2026-06-22T01:31:00Z",
      "thumbnail": null,
      "source": {
        "name": "DW",
        "color": "#C8102E"
      }
    },
    {
      "title": "Colombia election: Hard-right candidate claims victory",
      "link": "https://www.dw.com/en/colombia-election-hard-right-candidate-claims-victory/a-77650646?maca=en-rss-en-top-1022-rdf",
      "pubDate": "2026-06-22T00:59:00Z",
      "thumbnail": null,
      "source": {
        "name": "DW",
        "color": "#C8102E"
      }
    },
    {
      "title": "Deniz Undav: Germany&apos;s 2026 World Cup supersub",
      "link": "https://www.dw.com/en/deniz-undav-germany-s-2026-world-cup-supersub/a-77650649?maca=en-rss-en-top-1022-rdf",
      "pubDate": "2026-06-22T00:14:00Z",
      "thumbnail": null,
      "source": {
        "name": "DW",
        "color": "#C8102E"
      }
    },
    {
      "title": "Czechia: Thousands march in support of public media funding",
      "link": "https://www.dw.com/en/czechia-thousands-march-in-support-of-public-media-funding/a-77650608?maca=en-rss-en-top-1022-rdf",
      "pubDate": "2026-06-21T22:03:00Z",
      "thumbnail": null,
      "source": {
        "name": "DW",
        "color": "#C8102E"
      }
    },
    {
      "title": "Severe heat wave sweeps Europe, triggering alerts and disruptions",
      "link": "https://www.dw.com/en/severe-heat-wave-sweeps-europe-triggering-alerts-and-disruptions/a-77648446?maca=en-rss-en-top-1022-rdf",
      "pubDate": "2026-06-21T18:05:00Z",
      "thumbnail": null,
      "source": {
        "name": "DW",
        "color": "#C8102E"
      }
    }
  ],
  "lastUpdated": "2026-06-22T02:14:39.118Z"
}